Metadata-Version: 2.4
Name: llama-index-vector-stores-cassandra
Version: 0.4.1
Summary: llama-index vector_stores cassandra integration
Author-email: Your Name <you@example.com>
License-Expression: MIT
License-File: LICENSE
Requires-Python: <4.0,>=3.9
Requires-Dist: cassio<0.2,>=0.1.4
Requires-Dist: llama-index-core<0.15,>=0.13.0
